<?xml version = '1.0' encoding = 'UTF-8'?>
<relationalModel class="oracle.dbtools.crest.model.design.relational.RelationalDesign" name="Relational_1" id="0FEEC709-FEDD-C48E-4627-F06E83587364" mainViewID="978547FB-B2A4-C688-F0EA-F26049C7CF81">
<createdBy>Lisa</createdBy>
<createdTime>2014-03-01 07:10:33 UTC</createdTime>
<generatorID>Benutzergeneriert</generatorID>
<ownerDesignName>Datenbankentwurf</ownerDesignName>
<shouldBeOpen>false</shouldBeOpen>
<selectedRDBMSSite>32076570-2523-435C-2E92-BF29817DFF70</selectedRDBMSSite>
</relationalModel>